llama_index/tools/signnow/__init__.py
llama_index/tools/signnow/base.py
llama_index_tools_signnow-0.1.0.dist-info/METADATA
llama_index_tools_signnow-0.1.0.dist-info/WHEEL
llama_index_tools_signnow-0.1.0.dist-info/licenses/LICENSE
llama_index_tools_signnow-0.1.0.dist-info/RECORD
