Metadata-Version: 2.4
Name: llama-index-tools-signnow
Version: 0.1.0
Summary: SignNow MCP tools for LlamaIndex agents (expose SignNow MCP server tools as FunctionTool).
Author-email: mihasicehcek <lebedev.mikhail@pdffiller.team>
Maintainer: mihasicehcek
License-Expression: MIT
License-File: LICENSE
Keywords: mcp,signnow,tools
Requires-Python: <4.0,>=3.10
Requires-Dist: llama-index-core<0.15,>=0.13.0
Requires-Dist: llama-index-tools-mcp<0.5,>=0.4.1
Requires-Dist: mcp>=1.16.0
Requires-Dist: python-dotenv<2,>=1.0.0
Requires-Dist: signnow-mcp-server<1,>0.1
